README.md
setup.cfg
setup.py
powerbar/__init__.py
powerbar/bar.py
powerbar/progress.py
powerbar/tools.py
powerbar.egg-info/PKG-INFO
powerbar.egg-info/SOURCES.txt
powerbar.egg-info/dependency_links.txt
powerbar.egg-info/requires.txt
powerbar.egg-info/top_level.txt
powerbar.egg-info/zip-safe